README.txt
setup.py
lolpy/__init__.py
lolpy/api_client.py
lolpy/queue_type.py
lolpy/region.py
lolpy.egg-info/PKG-INFO
lolpy.egg-info/SOURCES.txt
lolpy.egg-info/dependency_links.txt
lolpy.egg-info/not-zip-safe
lolpy.egg-info/requires.txt
lolpy.egg-info/top_level.txt