Metadata-Version: 1.1
Name: lolpy
Version: 0.3
Summary: Package for Interaction with the League of Legends API
Home-page: https://github.com/abousquet/lolpy
Author: Adam Bousquet
Author-email: ajbousquet6@gmail.com
License: MIT
Platform: UNKNOWN
Classifier: Development Status :: 3 - Alpha
Classifier: Intended Audience :: Developers
Classifier: License :: OSI Approved :: MIT License
Classifier: Natural Language :: English
Classifier: Programming Language :: Python :: 3.6
Classifier: Topic :: Games/Entertainment :: Real Time Strategy
